qupython/__init__.py
qupython/construction.py
qupython/decorator.py
qupython/err_msg.py
qupython/function.py
qupython/qubit.py
qupython/typing.py
qupython-0.2.0.dist-info/LICENSE
qupython-0.2.0.dist-info/METADATA
qupython-0.2.0.dist-info/WHEEL
qupython-0.2.0.dist-info/top_level.txt
qupython-0.2.0.dist-info/RECORD
