Metadata-Version: 2.1
Name: qupython
Version: 0.2.0
Summary: Write quantum programs directly in Python
Author-email: Frank Harkins <frankharkins@hotmail.co.uk>
Project-URL: Homepage, https://github.com/frankharkins/qupython
Project-URL: Bug Tracker, https://github.com/frankharkins/qupython/issues
Classifier: Programming Language :: Python :: 3
Classifier: License :: OSI Approved :: MIT License
Classifier: Operating System :: OS Independent
Requires-Python: >=3.8
License-File: LICENSE
Requires-Dist: qiskit
Requires-Dist: qiskit-aer
